{"cameraMode":{"drawMode":0,"name":"Shaded","section":"Shading Mode"},"sceneLighting":true,"audioPlay":false,"sceneViewState":{"showFog":true,"showMaterialUpdate":false,"showSkybox":true,"showFlares":true,"showImageEffects":true,"showParticleSystems":true},"in2DMode":false,"pivot":{"x":107.27027893066406,"y":30.91982650756836,"z":-141.59059143066407},"rotation":{"x":-0.08039691299200058,"y":0.4934169352054596,"z":0.045869048684835437,"w":0.8648921847343445},"size":10.50432014465332,"orthographic":false}